{"__symbolic":"module","version":4,"metadata":{"initializeApp":{"__symbolic":"function"},"setupLoadingInterceptor":{"__symbolic":"function","parameters":["service"],"value":{"__symbolic":"new","expression":{"__symbolic":"reference","module":"@groupdocs.examples.angular/common-components","name":"LoadingMaskInterceptorService","line":50,"character":13},"arguments":[{"__symbolic":"reference","name":"service"}]}},"SignatureModule":{"__symbolic":"class","decorators":[{"__symbolic":"call","expression":{"__symbolic":"reference","module":"@angular/core","name":"NgModule","line":53,"character":1},"arguments":[{"declarations":[{"__symbolic":"reference","name":"SignatureAppComponent"},{"__symbolic":"reference","name":"SignatureListPanelComponent"},{"__symbolic":"reference","name":"ɵa"},{"__symbolic":"reference","name":"ɵb"},{"__symbolic":"reference","name":"ɵc"},{"__symbolic":"reference","name":"ɵd"},{"__symbolic":"reference","name":"ɵe"},{"__symbolic":"reference","name":"ɵf"},{"__symbolic":"reference","name":"ɵg"},{"__symbolic":"reference","name":"ɵh"},{"__symbolic":"reference","name":"ɵj"},{"__symbolic":"reference","name":"ɵk"},{"__symbolic":"reference","name":"ɵl"},{"__symbolic":"reference","name":"ɵm"}],"exports":[{"__symbolic":"reference","name":"SignatureAppComponent"},{"__symbolic":"reference","name":"SignatureListPanelComponent"},{"__symbolic":"reference","name":"ɵa"},{"__symbolic":"reference","name":"ɵb"},{"__symbolic":"reference","name":"ɵc"},{"__symbolic":"reference","name":"ɵd"},{"__symbolic":"reference","name":"ɵe"},{"__symbolic":"reference","name":"ɵf"},{"__symbolic":"reference","name":"ɵg"},{"__symbolic":"reference","name":"ɵh"},{"__symbolic":"reference","name":"ɵj"},{"__symbolic":"reference","name":"ɵk"},{"__symbolic":"reference","name":"ɵl"},{"__symbolic":"reference","name":"ɵm"},{"__symbolic":"reference","module":"@groupdocs.examples.angular/common-components","name":"CommonComponentsModule","line":82,"character":4}],"imports":[{"__symbolic":"reference","module":"@angular/common","name":"CommonModule","line":83,"character":12},{"__symbolic":"reference","module":"@groupdocs.examples.angular/common-components","name":"CommonComponentsModule","line":84,"character":4},{"__symbolic":"reference","module":"@angular/common/http","name":"HttpClientModule","line":85,"character":4},{"__symbolic":"reference","module":"@fortawesome/angular-fontawesome","name":"FontAwesomeModule","line":86,"character":4},{"__symbolic":"reference","module":"ng-click-outside","name":"ClickOutsideModule","line":87,"character":4}],"providers":[{"__symbolic":"reference","name":"SignatureService"},{"__symbolic":"reference","module":"@groupdocs.examples.angular/common-components","name":"ConfigService","line":90,"character":4},{"__symbolic":"reference","name":"SignatureConfigService"},{"__symbolic":"reference","name":"SelectSignatureService"},{"__symbolic":"reference","name":"DragSignatureService"},{"__symbolic":"reference","name":"RemoveSignatureService"},{"__symbolic":"reference","name":"ActiveSignatureService"},{"__symbolic":"reference","name":"ActiveCanvasService"},{"__symbolic":"reference","name":"ɵi"},{"__symbolic":"reference","module":"@angular/common","name":"DatePipe","line":98,"character":4},{"__symbolic":"reference","name":"SignaturesHolderService"},{"__symbolic":"reference","name":"SignatureTabActivatorService"},{"__symbolic":"reference","name":"CopySignatureService"},{"provide":{"__symbolic":"reference","module":"@angular/common/http","name":"HTTP_INTERCEPTORS","line":103,"character":15},"useClass":{"__symbolic":"reference","module":"@groupdocs.examples.angular/common-components","name":"ErrorInterceptorService","line":104,"character":16},"multi":true},{"provide":{"__symbolic":"reference","module":"@angular/core","name":"APP_INITIALIZER","line":108,"character":15},"useFactory":{"__symbolic":"reference","name":"initializeApp"},"deps":[{"__symbolic":"reference","name":"SignatureConfigService"}],"multi":true},{"__symbolic":"reference","module":"@groupdocs.examples.angular/common-components","name":"LoadingMaskService","line":112,"character":4},{"provide":{"__symbolic":"reference","module":"@angular/common/http","name":"HTTP_INTERCEPTORS","line":114,"character":15},"useFactory":{"__symbolic":"reference","name":"setupLoadingInterceptor"},"multi":true,"deps":[{"__symbolic":"reference","module":"@groupdocs.examples.angular/common-components","name":"LoadingMaskService","line":117,"character":13}]}],"entryComponents":[{"__symbolic":"reference","name":"ɵe"},{"__symbolic":"reference","name":"ɵh"}]}]}],"members":{"__ctor__":[{"__symbolic":"constructor"}]}},"SignatureAppComponent":{"__symbolic":"class","decorators":[{"__symbolic":"call","expression":{"__symbolic":"reference","module":"@angular/core","name":"Component","line":48,"character":1},"arguments":[{"selector":"gd-signature","template":"<gd-loading-mask [loadingMask]=\"isLoading\"></gd-loading-mask>\n<div class=\"wrapper\" (contextmenu)=\"onRightClick($event)\" (click)=\"hideAll($event)\">\n  <div class=\"signature-wrapper wrapper\">\n    <gd-tabbed-toolbars [logo]=\"'signature'\" [icon]=\"'pen-square'\">\n      <gd-tabs>\n        <gd-tab [tabTitle]=\"'File'\" [icon]=\"'folder-open'\" [id]=\"'1'\" [active]=\"true\">\n          <div id=\"files-tools\" class=\"toolbar-panel\">\n            <gd-button [icon]=\"'folder-open'\" [tooltip]=\"'Browse files'\" (click)=\"openModal(browseFilesModal)\"\n                       *ngIf=\"browseConfig\"></gd-button>\n\n            <gd-button [disabled]=\"formatDisabled\" [icon]=\"'download'\" [tooltip]=\"'Download'\"\n                       (click)=\"downloadFile()\" *ngIf=\"downloadConfig\"></gd-button>\n            <gd-button [disabled]=\"formatDisabled\" [icon]=\"'save'\" [tooltip]=\"'Save'\" (click)=\"sign()\"></gd-button>\n\n          </div>\n        </gd-tab>\n        <gd-tab [tabTitle]=\"'Signatures'\" [icon]=\"'signature'\" [id]=\"'2'\">\n          <div class=\"toolbar-panel\">\n            <div *ngFor=\"let signatureType of signatureTypes\">\n              <gd-signature-tab [disabled]=\"!file\" *ngIf=\"isVisible(signatureType.id)\"\n                                [icon]=\"signatureType.icon\" (activeTab)=\"activeTab($event)\"\n                                [id]=\"signatureType.id\" [tooltip]=\"signatureType.name\">\n              </gd-signature-tab>\n            </div>\n          </div>\n        </gd-tab>\n        <gd-tab [tabTitle]=\"''\" [icon]=\"'qrcode'\" [id]=\"'3'\" *ngIf=\"!isDesktop && codesConfig()\">\n          <div class=\"toolbar-panel\">\n            <div *ngFor=\"let signatureType of signatureTypeCodes\">\n              <gd-signature-tab [disabled]=\"!file\" *ngIf=\"getSignatureTypeConfig(signatureType.id)\"\n                                [icon]=\"signatureType.icon\" (activeTab)=\"activeTab($event)\"\n                                [id]=\"signatureType.id\" [tooltip]=\"signatureType.name\">\n              </gd-signature-tab>\n            </div>\n          </div>\n        </gd-tab>\n      </gd-tabs>\n    </gd-tabbed-toolbars>\n    <gd-signature-left-panel *ngIf=\"activeSignatureTab\" [rewrite]=\"rewriteConfig\" (newSignatureEvent)=\"newSign($event)\"\n                             [isPdf]=\"isPdf()\" [id]=\"activeSignatureTab\">\n    </gd-signature-left-panel>\n    <div class=\"doc-panel\" *ngIf=\"file\">\n      <gd-document (drop)=\"dropSignature($event)\" (dragover)=\"dragOver($event)\" class=\"gd-document\" *ngIf=\"file\"\n                   [file]=\"file\" [mode]=\"htmlModeConfig\" gdScrollable\n                   [preloadPageCount]=\"preloadPageCountConfig\" gdRenderPrint [htmlMode]=\"htmlModeConfig\"></gd-document>\n    </div>\n\n    <gd-init-state [icon]=\"'signature'\" [text]=\"'Drop file here to upload'\" *ngIf=\"!file\"\n                   (fileDropped)=\"fileDropped($event)\">\n      Click\n      <fa-icon [icon]=\"['fas','folder-open']\"></fa-icon>\n      to open file<br>\n      Or drop file here\n    </gd-init-state>\n    <gd-hand-modal></gd-hand-modal>\n    <gd-stamp-modal></gd-stamp-modal>\n  </div>\n  <gd-browse-files-modal (urlForUpload)=\"upload($event)\" [files]=\"files\" (selectedDirectory)=\"selectDir($event)\"\n                         (selectedFileGuid)=\"selectFile($event, null, browseFilesModal)\"\n                         [uploadConfig]=\"uploadConfig\"></gd-browse-files-modal>\n\n  <gd-error-modal></gd-error-modal>\n  <gd-password-required></gd-password-required>\n  <gd-success-modal></gd-success-modal>\n</div>\n","styles":["@import url(https://fonts.googleapis.com/css?family=Open+Sans&display=swap);:host *{font-family:'Open Sans',Arial,Helvetica,sans-serif}::ng-deep .page{position:relative}::ng-deep .gd-page-image{width:unset;height:unset}::ng-deep .top-panel{align-content:flex-start}.wrapper{align-items:stretch;height:100%;width:100%;position:fixed;top:0;bottom:0;left:0;right:0}.doc-panel{display:flex;height:inherit}.gd-document{width:100%;height:calc(100% - 90px)}.toolbar-panel{width:100%;display:flex;align-items:center}.signature-wrapper ::ng-deep .button{color:#3e4e5a!important}.signature-wrapper ::ng-deep .button .text{padding:0!important}@media (max-width:1037px){::ng-deep .panzoom{justify-content:unset!important}::ng-deep .logo ::ng-deep .icon{font-size:24px!important}::ng-deep .top-panel{height:120px!important}}"]}]}],"members":{"__ctor__":[{"__symbolic":"constructor","parameters":[{"__symbolic":"reference","name":"SignatureService"},{"__symbolic":"reference","module":"@groupdocs.examples.angular/common-components","name":"ModalService","line":83,"character":37},{"__symbolic":"reference","name":"SignatureConfigService"},{"__symbolic":"reference","module":"@groupdocs.examples.angular/common-components","name":"UploadFilesService","line":85,"character":34},{"__symbolic":"reference","module":"@groupdocs.examples.angular/common-components","name":"NavigateService","line":86,"character":40},{"__symbolic":"reference","module":"@groupdocs.examples.angular/common-components","name":"ZoomService","line":87,"character":36},{"__symbolic":"reference","module":"@groupdocs.examples.angular/common-components","name":"PagePreloadService","line":88,"character":34},{"__symbolic":"reference","module":"@groupdocs.examples.angular/common-components","name":"RenderPrintService","line":89,"character":43},{"__symbolic":"reference","module":"@groupdocs.examples.angular/common-components","name":"PasswordService","line":90,"character":31},{"__symbolic":"reference","module":"@groupdocs.examples.angular/common-components","name":"WindowService","line":91,"character":38},{"__symbolic":"reference","name":"SelectSignatureService"},{"__symbolic":"reference","name":"SignatureTabActivatorService"},{"__symbolic":"reference","module":"@groupdocs.examples.angular/common-components","name":"HostingDynamicComponentService","line":94,"character":49},{"__symbolic":"reference","module":"@groupdocs.examples.angular/common-components","name":"AddDynamicComponentService","line":95,"character":51},{"__symbolic":"reference","name":"DragSignatureService"},{"__symbolic":"reference","module":"@groupdocs.examples.angular/common-components","name":"OnCloseService","line":97,"character":39},{"__symbolic":"reference","name":"RemoveSignatureService"},{"__symbolic":"reference","name":"ActiveSignatureService"},{"__symbolic":"reference","module":"@groupdocs.examples.angular/common-components","name":"ExceptionMessageService","line":100,"character":42},{"__symbolic":"reference","name":"SignaturesHolderService"},{"__symbolic":"reference","module":"@groupdocs.examples.angular/common-components","name":"TabActivatorService","line":102,"character":44},{"__symbolic":"reference","name":"CopySignatureService"}]}],"createDraggableSign":[{"__symbolic":"method"}],"createAddedSignature":[{"__symbolic":"method"}],"ngOnInit":[{"__symbolic":"method"}],"defaultDocumentConfig":[{"__symbolic":"method"}],"openModal":[{"__symbolic":"method"}],"closeModal":[{"__symbolic":"method"}],"selectDir":[{"__symbolic":"method"}],"selectFile":[{"__symbolic":"method"}],"preloadPages":[{"__symbolic":"method"}],"upload":[{"__symbolic":"method"}],"downloadFile":[{"__symbolic":"method"}],"clearData":[{"__symbolic":"method"}],"onRightClick":[{"__symbolic":"method"}],"getSignatureTypeConfig":[{"__symbolic":"method"}],"dragOver":[{"__symbolic":"method"}],"dropSignature":[{"__symbolic":"method"}],"selectSignature":[{"__symbolic":"method"}],"addSignatureComponent":[{"__symbolic":"method"}],"closeTab":[{"__symbolic":"method"}],"hideAll":[{"__symbolic":"method"}],"newSign":[{"__symbolic":"method"}],"addTextSign":[{"__symbolic":"method"}],"ngOnDestroy":[{"__symbolic":"method"}],"cleanSignatures":[{"__symbolic":"method"}],"sign":[{"__symbolic":"method"}],"prepareSignaturesData":[{"__symbolic":"method"}],"isPdf":[{"__symbolic":"method"}],"codesConfig":[{"__symbolic":"method"}],"isVisible":[{"__symbolic":"method"}],"activeTab":[{"__symbolic":"method"}],"fileDropped":[{"__symbolic":"method"}]}},"SignatureService":{"__symbolic":"class","decorators":[{"__symbolic":"call","expression":{"__symbolic":"reference","module":"@angular/core","name":"Injectable","line":6,"character":1},"arguments":[{"providedIn":"root"}]}],"members":{"__ctor__":[{"__symbolic":"constructor","parameters":[{"__symbolic":"reference","module":"@angular/common/http","name":"HttpClient","line":11,"character":29},{"__symbolic":"reference","module":"@groupdocs.examples.angular/common-components","name":"ConfigService","line":11,"character":58}]}],"loadFiles":[{"__symbolic":"method"}],"loadFile":[{"__symbolic":"method"}],"upload":[{"__symbolic":"method"}],"loadPage":[{"__symbolic":"method"}],"getDownloadUrl":[{"__symbolic":"method"}],"loadPrint":[{"__symbolic":"method"}],"loadPrintPdf":[{"__symbolic":"method"}],"getSignatures":[{"__symbolic":"method"}],"removeSignatures":[{"__symbolic":"method"}],"uploadSignature":[{"__symbolic":"method"}],"getCode":[{"__symbolic":"method"}],"loadSignatureImage":[{"__symbolic":"method"}],"saveTextSignature":[{"__symbolic":"method"}],"toRgb":[{"__symbolic":"method"}],"toHex":[{"__symbolic":"method"}],"saveImage":[{"__symbolic":"method"}],"saveStamp":[{"__symbolic":"method"}],"sign":[{"__symbolic":"method"}],"downloadSigned":[{"__symbolic":"method"}]},"statics":{"ngInjectableDef":{}}},"SignatureConfigService":{"__symbolic":"class","decorators":[{"__symbolic":"call","expression":{"__symbolic":"reference","module":"@angular/core","name":"Injectable","line":6,"character":1},"arguments":[{"providedIn":"root"}]}],"members":{"__ctor__":[{"__symbolic":"constructor","parameters":[{"__symbolic":"reference","module":"@angular/common/http","name":"HttpClient","line":14,"character":29},{"__symbolic":"reference","module":"@groupdocs.examples.angular/common-components","name":"ConfigService","line":14,"character":58}]}],"load":[{"__symbolic":"method"}]},"statics":{"ngInjectableDef":{}}},"SignatureListPanelComponent":{"__symbolic":"class","decorators":[{"__symbolic":"call","expression":{"__symbolic":"reference","module":"@angular/core","name":"Component","line":9,"character":1},"arguments":[{"selector":"gd-signature-list-panel","template":"<div class=\"gd-signature-list-wrapper\">\n  <div class=\"gd-signature-list-scroll\" *ngIf=\"signatures\">\n    <div class=\"gd-signature-list\" *ngIf=\"signatures\">\n      <div class=\"gd-signature\" *ngFor=\"let signature of signatures\">\n        <div class=\"gd-signature-item\" [draggable]=\"isDigital() ? false : true\"\n             (dragover)=\"dragOver($event)\" (dragstart)=\"dragStart($event)\"\n             (dragleave)=\"dragLeave($event, signature.guid)\" (drop)=\"drop($event)\">\n          <div class=\"gd-signature-thumbnail\" *ngIf=\"isDigital()\" (click)=\"select(signature.guid)\">\n            <fa-icon [icon]=\"['fa','fingerprint']\" [class]=\"'ng-fa-icon icon'\"></fa-icon>\n          </div>\n          <div class=\"gd-signature-thumbnail\" *ngIf=\"signature.image\">\n            <img [ngClass]=\"'gd-signature-thumbnail-' + signatureType\"\n                 [attr.src]=\"getImage(signature.image) | safeResourceHtml\"\n                 alt=\"\" [draggable]=\"false\" (click)=\"select(signature.guid)\">\n          </div>\n          <div class=\"gd-signature-title\" [ngClass]=\"signatureType\" (click)=\"select(signature.guid)\">\n            <label class=\"gd-signature-name\" [style.color]=\"signature.fontColor\">\n              {{signature.text ? signature.text : signature.name}}</label>\n          </div>\n          <div class=\"gd-signature-trash-icon\">\n            <fa-icon [icon]=\"['fas','trash']\" [class]=\"'ng-fa-icon icon'\"\n                     (click)=\"deleteSign(signature.guid)\"></fa-icon>\n          </div>\n        </div>\n        <div class=\"gd-digital-inputs\" *ngIf=\"showDigitalInputs && digitalId === signature.guid\">\n          <div class=\"gd-digital-input-wrapper\">\n            <fa-icon [icon]=\"['fas','comment']\" [class]=\"'ng-fa-icon icon'\"></fa-icon>\n            <input #reason (input)=\"digitalProps.reason = reason.value\" type=\"text\" placeholder=\"Reason\">\n          </div>\n          <div class=\"gd-digital-input-wrapper\" *ngIf=\"isPdf\">\n            <fa-icon [icon]=\"['fas','envelope']\" [class]=\"'ng-fa-icon icon'\"></fa-icon>\n            <input #contact (input)=\"digitalProps.contact = contact.value\" type=\"text\" placeholder=\"Contact\">\n          </div>\n          <div class=\"gd-digital-input-wrapper\" *ngIf=\"isPdf\">\n            <fa-icon [icon]=\"['fas','map-marker-alt']\" [class]=\"'ng-fa-icon icon'\"></fa-icon>\n            <input #address (input)=\"digitalProps.address = address.value\" type=\"text\" placeholder=\"Location\">\n          </div>\n          <div class=\"gd-digital-input-wrapper\">\n            <fa-icon [icon]=\"['fas','key']\" [class]=\"'ng-fa-icon icon'\"></fa-icon>\n            <input #password (input)=\"digitalProps.signaturePassword = password.value\" type=\"password\"\n                   placeholder=\"Password\">\n          </div>\n          <div class=\"gd-digital-input-wrapper\">\n            <fa-icon [icon]=\"['fas','calendar']\" [class]=\"'ng-fa-icon icon'\"></fa-icon>\n            <input type=\"date\" #date (input)=\"digitalProps.date=parseDate(date.value)\" placeholder=\"Date\">\n          </div>\n          <div class=\"gd-sign-digital\" [ngClass]=\"isActive(signature.guid) ? 'active' : ''\"\n               (click)=\"selectDigital(signature.guid)\">\n            <fa-icon [icon]=\"['fas','save']\"></fa-icon>\n            <span class=\"digital-apply\">Apply</span>\n          </div>\n        </div>\n      </div>\n    </div>\n  </div>\n  <div class=\"gd-signature-empty-list\" *ngIf=\"empty()\">\n    <fa-icon *ngIf=\"icon\" [icon]=\"['fas',icon]\" [class]=\"'ng-fa-icon icon'\"></fa-icon>\n    <span class=\"gd-empty-list-text\">There is no entries yet</span>\n  </div>\n</div>\n","styles":[".gd-signature-list-wrapper{display:flex;flex-direction:column;flex:1;overflow:auto;height:100%}.gd-signature-list-scroll{display:block;overflow-x:hidden;overflow-y:auto!important}.gd-signature-item{width:100%;cursor:pointer;position:relative;min-height:68px;display:flex;flex-direction:row;background-color:rgba(255,255,255)}.gd-signature-item .icon{font-size:15px;color:#676767;cursor:pointer}.gd-signature-item .gd-signature-trash-icon{flex:0 0 70px;display:flex;align-items:center;justify-content:center}.gd-signature-item .gd-signature-name{max-width:130px;font-size:13px;color:rgba(0,0,0,.36);cursor:pointer;text-overflow:ellipsis;white-space:nowrap;display:block;overflow:hidden}.gd-signature-item .gd-signature-thumbnail{flex:0 0 70px;display:flex;align-items:center;justify-content:center;width:auto}.gd-signature-item .gd-signature-thumbnail .icon{font-size:30px;padding:0;margin:0;opacity:.25}.gd-signature-item .gd-signature-title{flex:1;display:flex;align-items:center;justify-content:flex-start;padding-left:7px}.gd-signature-item .gd-signature-thumbnail-hand,.gd-signature-item .gd-signature-thumbnail-image,.gd-signature-item .gd-signature-thumbnail-text{max-width:70px;height:41px}.gd-signature-item .gd-signature-thumbnail-image{min-width:41px;max-width:70px}.gd-signature-item .gd-signature-thumbnail-barCode,.gd-signature-item .gd-signature-thumbnail-qrCode{max-width:70px;height:44px}.gd-signature-item .gd-signature-thumbnail-stamp{max-width:70px;height:48px}.gd-signature-item .gd-signature-title.text{padding-left:16px}.gd-signature-list{display:flex;flex-direction:column;width:inherit;background-color:#e7e7e7}.gd-signature{display:flex;flex-direction:column;width:100%;background-color:rgba(255,255,255,.75);margin-bottom:2px}.gd-signature-empty-list{display:flex;flex-direction:column;text-align:center;color:#acacac;justify-content:center;width:350px;height:250px}.gd-signature-empty-list .icon{font-size:60px}.gd-signature-empty-list i{font-size:60px;padding:87px 97px 0}.gd-empty-list-text{padding:18px 38px 0;font-size:12px}.gd-digital-input-wrapper{margin:9px 8px 7px;display:flex;border:5px #ddd}.gd-sign-digital{height:27px;background-color:#969696;margin:9px 8px 7px;display:flex;color:#fff;font-size:13px;box-shadow:0 0 3px #ddd;cursor:pointer;padding-top:5px;padding-left:10px}.digital-apply{padding-left:10px}.gd-sign-digital.active{background-color:#25c2d4}.gd-digital-inputs input{width:100%;height:27px;padding-left:28px}.gd-digital-inputs .icon{position:absolute;font-size:12px;margin:7px 0 7px 7px;color:#ccc!important}@media (max-width:1037px){.gd-signature-item .gd-signature-name{font-size:13px}.gd-signature-item .icon{font-size:15px}.gd-signature-thumbnail-hand,.gd-signature-thumbnail-image,.gd-signature-thumbnail-text{margin:0}.gd-signature-thumbnail-image{width:44px;height:44px}.gd-signature-thumbnail-digital .icon{font-size:30px!important}.gd-digital-inputs .icon{font-size:13px}}"]}]}],"members":{"signatures":[{"__symbolic":"property","decorators":[{"__symbolic":"call","expression":{"__symbolic":"reference","module":"@angular/core","name":"Input","line":16,"character":3}}]}],"icon":[{"__symbolic":"property","decorators":[{"__symbolic":"call","expression":{"__symbolic":"reference","module":"@angular/core","name":"Input","line":17,"character":3}}]}],"signatureType":[{"__symbolic":"property","decorators":[{"__symbolic":"call","expression":{"__symbolic":"reference","module":"@angular/core","name":"Input","line":18,"character":3}}]}],"isPdf":[{"__symbolic":"property","decorators":[{"__symbolic":"call","expression":{"__symbolic":"reference","module":"@angular/core","name":"Input","line":19,"character":3}}]}],"loading":[{"__symbolic":"property","decorators":[{"__symbolic":"call","expression":{"__symbolic":"reference","module":"@angular/core","name":"Input","line":20,"character":3}}]}],"removeSignatureEvent":[{"__symbolic":"property","decorators":[{"__symbolic":"call","expression":{"__symbolic":"reference","module":"@angular/core","name":"Output","line":21,"character":3}}]}],"__ctor__":[{"__symbolic":"constructor","parameters":[{"__symbolic":"reference","module":"@groupdocs.examples.angular/common-components","name":"NavigateService","line":26,"character":40},{"__symbolic":"reference","name":"SelectSignatureService"},{"__symbolic":"reference","name":"DragSignatureService"},{"__symbolic":"reference","module":"@angular/common","name":"DatePipe","line":29,"character":33},{"__symbolic":"reference","name":"SignaturesHolderService"}]}],"ngOnInit":[{"__symbolic":"method"}],"getImage":[{"__symbolic":"method"}],"deleteSign":[{"__symbolic":"method"}],"isDigital":[{"__symbolic":"method"}],"selectSignature":[{"__symbolic":"method"}],"getSign":[{"__symbolic":"method"}],"select":[{"__symbolic":"method"}],"dragOver":[{"__symbolic":"method"}],"dragLeave":[{"__symbolic":"method"}],"selectDigital":[{"__symbolic":"method"}],"parseDate":[{"__symbolic":"method"}],"isActive":[{"__symbolic":"method"}],"dragStart":[{"__symbolic":"method"}],"empty":[{"__symbolic":"method"}],"ngOnChanges":[{"__symbolic":"method"}],"drop":[{"__symbolic":"method"}]}},"SelectSignatureService":{"__symbolic":"class","members":{"__ctor__":[{"__symbolic":"constructor"}],"select":[{"__symbolic":"method"}]}},"RemoveSignatureService":{"__symbolic":"class","members":{"__ctor__":[{"__symbolic":"constructor"}],"remove":[{"__symbolic":"method"}]}},"CopySignatureService":{"__symbolic":"class","members":{"__ctor__":[{"__symbolic":"constructor"}],"copy":[{"__symbolic":"method"}],"notifyChanges":[{"__symbolic":"method"}]}},"ActiveSignatureService":{"__symbolic":"class","members":{"__ctor__":[{"__symbolic":"constructor"}],"changeActive":[{"__symbolic":"method"}]}},"ActiveCanvasService":{"__symbolic":"class","members":{"__ctor__":[{"__symbolic":"constructor"}],"changeActive":[{"__symbolic":"method"}]}},"SignaturesHolderService":{"__symbolic":"class","members":{"__ctor__":[{"__symbolic":"constructor"}],"add":[{"__symbolic":"method"}],"addId":[{"__symbolic":"method"}],"delete":[{"__symbolic":"method"}],"has":[{"__symbolic":"method"}],"clear":[{"__symbolic":"method"}],"values":[{"__symbolic":"method"}],"get":[{"__symbolic":"method"}],"remove":[{"__symbolic":"method"}],"changeTemp":[{"__symbolic":"method"}]}},"SignatureTabActivatorService":{"__symbolic":"class","extends":{"__symbolic":"reference","module":"@groupdocs.examples.angular/common-components","name":"TabActivatorService","line":2,"character":50},"members":{"__ctor__":[{"__symbolic":"constructor"}]}},"DragSignatureService":{"__symbolic":"class","members":{"__ctor__":[{"__symbolic":"constructor"}]}},"ɵa":{"__symbolic":"class","decorators":[{"__symbolic":"call","expression":{"__symbolic":"reference","module":"@angular/core","name":"Component","line":7,"character":1},"arguments":[{"selector":"gd-signature-tab","template":"<div class=\"gd-tab\" (mousedown)=\"toggleTab()\" gdTooltip\n     (showToolTip)=\"showToolTip = $event\" [ngClass]=\"(active) ? 'active' : ''\">\n  <fa-icon *ngIf=\"icon\" [icon]=\"['fas',icon]\" [class]=\"'ng-fa-icon icon'\"></fa-icon>\n  <gd-tooltip [text]=\"tooltip\" [show]=\"showToolTip\"\n              *ngIf=\"tooltip\"></gd-tooltip>\n</div>\n","styles":[".gd-tab{font-size:14px;color:#3e4e5a;cursor:pointer;display:flex;align-items:center;justify-content:center;min-width:36px;height:36px;text-align:center;position:relative;white-space:nowrap;padding:0!important;margin:0 10px}.gd-tab.active{background-color:#acacac;color:#fff!important;font-weight:700}.gd-tab ::ng-deep .tooltip{font-size:12px;margin:20px -57px}.gd-tab .title{margin:auto 23px}@media (max-width:1037px){.gd-tab{font-size:20px}}"]}]}],"members":{"id":[{"__symbolic":"property","decorators":[{"__symbolic":"call","expression":{"__symbolic":"reference","module":"@angular/core","name":"Input","line":13,"character":3}}]}],"icon":[{"__symbolic":"property","decorators":[{"__symbolic":"call","expression":{"__symbolic":"reference","module":"@angular/core","name":"Input","line":14,"character":3}}]}],"disabled":[{"__symbolic":"property","decorators":[{"__symbolic":"call","expression":{"__symbolic":"reference","module":"@angular/core","name":"Input","line":15,"character":3}}]}],"tooltip":[{"__symbolic":"property","decorators":[{"__symbolic":"call","expression":{"__symbolic":"reference","module":"@angular/core","name":"Input","line":16,"character":3}}]}],"activeTab":[{"__symbolic":"property","decorators":[{"__symbolic":"call","expression":{"__symbolic":"reference","module":"@angular/core","name":"Output","line":17,"character":3}}]}],"__ctor__":[{"__symbolic":"constructor","parameters":[{"__symbolic":"reference","name":"SignatureTabActivatorService"},{"__symbolic":"reference","module":"@groupdocs.examples.angular/common-components","name":"ModalService","line":22,"character":37},{"__symbolic":"reference","module":"@groupdocs.examples.angular/common-components","name":"ExceptionMessageService","line":23,"character":42}]}],"activation":[{"__symbolic":"method"}],"ngOnInit":[{"__symbolic":"method"}],"toggleTab":[{"__symbolic":"method"}]}},"ɵb":{"__symbolic":"class","decorators":[{"__symbolic":"call","expression":{"__symbolic":"reference","module":"@angular/core","name":"Component","line":6,"character":1},"arguments":[{"selector":"gd-new-bar-qr-code","template":"<div class=\"gd-qr-container\">\n  <div class=\"gd-qr-preview-container\">\n    <img class=\"gd-signature-thumbnail-image\" [attr.src]=\"getData()\" alt *ngIf=\"encodedImage\">\n    <div class=\"gd-empty-code\" *ngIf=\"!encodedImage\">\n      <fa-icon [icon]=\"['fa',icon]\" [class]=\"'ng-fa-icon icon'\"></fa-icon>\n    </div>\n  </div>\n  <div class=\"new-signature-input-group\">\n    <input type=\"text\" class=\"gd-qr-property\" #text (keyup)=\"saveTemp(text.value)\" (keyup.enter)=\"addSign(text.value)\"\n           placeholder=\"{{name}}\" id=\"text-input\"/>\n    <div class=\"gd-add-optical\" [ngClass]=\"text.value ? 'active' : 'inactive'\" (click)=\"addSign(text.value)\">\n      <fa-icon [icon]=\"['fa','plus']\" [class]=\"'ng-fa-icon icon'\"></fa-icon>\n    </div>\n  </div>\n</div>\n","styles":[".gd-sign-digital.active{background-color:#3787f5}.gd-sign-digital{height:27px;background-color:#969696;margin:9px 8px 7px;text-align:center;color:#fff;font-size:13px;box-shadow:0 0 3px #ddd;cursor:pointer;padding-top:5px}.gd-qr-container{font-family:\"Open Sans\",\"Helvetica Neue\",Helvetica,Arial,sans-serif;background-color:#e7e7e7}.gd-qr-container input:focus{border:2px solid #00c4d7;transition:border-color .3s linear}.gd-qr-preview-container{text-align:center;background-color:#fff;margin-bottom:1px;height:350px}.gd-qr-preview-container .gd-empty-code{color:#ccc;font-size:60px;width:350px;height:350px;justify-content:center;display:flex;align-items:center}.gd-qr-preview-container .gd-signature-thumbnail-image{min-width:41px;width:100%;height:100%;margin:0}.new-signature-input-group{display:flex;flex-direction:row;align-items:center;height:70px;background-color:#fff;justify-content:center}.gd-qr-property{font-size:12px;width:80%;border:2px solid #ddd;padding:5px;outline:0;color:#3a4e5b}.gd-add-optical{width:32px;height:29px;display:flex;justify-content:center;align-items:center;background-color:#3787f5;cursor:pointer}.gd-add-optical .icon{color:#fff;line-height:28px}.gd-add-optical.active{background-color:#25c2d4}.gd-add-optical.inactive{background-color:#646464}.gd-add-optical:hover{box-shadow:transparent 0 0 3px}@media (max-width:1037px){.gd-qr-container{margin:0 13px 0 12px}}"]}]}],"members":{"type":[{"__symbolic":"property","decorators":[{"__symbolic":"call","expression":{"__symbolic":"reference","module":"@angular/core","name":"Input","line":12,"character":3}}]}],"icon":[{"__symbolic":"property","decorators":[{"__symbolic":"call","expression":{"__symbolic":"reference","module":"@angular/core","name":"Input","line":13,"character":3}}]}],"name":[{"__symbolic":"property","decorators":[{"__symbolic":"call","expression":{"__symbolic":"reference","module":"@angular/core","name":"Input","line":14,"character":3}}]}],"closePanel":[{"__symbolic":"property","decorators":[{"__symbolic":"call","expression":{"__symbolic":"reference","module":"@angular/core","name":"Output","line":15,"character":3}}]}],"__ctor__":[{"__symbolic":"constructor","parameters":[{"__symbolic":"reference","name":"SignatureService"},{"__symbolic":"reference","module":"@angular/core","name":"ElementRef","line":21,"character":35}]}],"saveCode":[{"__symbolic":"method"}],"clean":[{"__symbolic":"method"}],"ngOnInit":[{"__symbolic":"method"}],"addSign":[{"__symbolic":"method"}],"saveTemp":[{"__symbolic":"method"}],"getData":[{"__symbolic":"method"}]}},"ɵc":{"__symbolic":"class","decorators":[{"__symbolic":"call","expression":{"__symbolic":"reference","module":"@angular/core","name":"Component","line":4,"character":1},"arguments":[{"selector":"gd-upload-signature","template":"<div class=\"gd-upload-signature\" gdDndSignature (files)=\"uploadFiles($event)\">\n  <div class=\"gd-upload-inputs\">\n    <input type=\"file\" (change)=\"handleFileInput($event.target.files)\"/>\n    <fa-icon [icon]=\"['fas','folder-open']\" [class]=\"'ng-fa-icon icon'\"></fa-icon>\n    <div class=\"gd-upload-title\">\n      <p class=\"text\">Click\n        <fa-icon [icon]=\"['fas','folder-open']\"></fa-icon>\n        to open file\n      </p>\n      <p class=\"text\">Or drop file here</p>\n    </div>\n  </div>\n</div>\n","styles":[".gd-upload-inputs{height:350px;text-align:center;display:flex;flex-direction:column;justify-content:center;align-content:center;background-color:#fff}.gd-upload-inputs .icon{font-size:52px;color:#959da5}.gd-upload-inputs input{opacity:0;position:absolute;cursor:pointer;width:-webkit-fit-content;width:-moz-fit-content;width:fit-content;height:203px}.gd-upload-title{color:#bababa;font-size:13px;margin:10px 0 0}.text{font-size:12px;text-align:center}@media (max-width:1037px){.gd-upload-inputs{width:-webkit-fill-available}.gd-upload-inputs input{width:-webkit-fill-available;height:201px}}"]}]}],"members":{"signatureType":[{"__symbolic":"property","decorators":[{"__symbolic":"call","expression":{"__symbolic":"reference","module":"@angular/core","name":"Input","line":10,"character":3}}]}],"rewrite":[{"__symbolic":"property","decorators":[{"__symbolic":"call","expression":{"__symbolic":"reference","module":"@angular/core","name":"Input","line":11,"character":3}}]}],"closePanel":[{"__symbolic":"property","decorators":[{"__symbolic":"call","expression":{"__symbolic":"reference","module":"@angular/core","name":"Output","line":12,"character":3}}]}],"__ctor__":[{"__symbolic":"constructor","parameters":[{"__symbolic":"reference","name":"SignatureService"}]}],"ngOnInit":[{"__symbolic":"method"}],"handleFileInput":[{"__symbolic":"method"}],"addFiles":[{"__symbolic":"method"}],"uploadFiles":[{"__symbolic":"method"}]}},"ɵd":{"__symbolic":"class","extends":{"__symbolic":"reference","module":"@groupdocs.examples.angular/common-components","name":"DndDirective","line":6,"character":43},"decorators":[{"__symbolic":"call","expression":{"__symbolic":"reference","module":"@angular/core","name":"Directive","line":3,"character":1},"arguments":[{"selector":"[gdDndSignature]"}]}],"members":{"files":[{"__symbolic":"property","decorators":[{"__symbolic":"call","expression":{"__symbolic":"reference","module":"@angular/core","name":"Output","line":7,"character":3}}]}],"__ctor__":[{"__symbolic":"constructor","parameters":[{"__symbolic":"reference","module":"@groupdocs.examples.angular/common-components","name":"UploadFilesService","line":9,"character":35}]}],"onDrop":[{"__symbolic":"method","decorators":[{"__symbolic":"call","expression":{"__symbolic":"reference","module":"@angular/core","name":"HostListener","line":13,"character":3},"arguments":["drop",["$event"]]}]}]}},"ɵe":{"__symbolic":"class","decorators":[{"__symbolic":"call","expression":{"__symbolic":"reference","module":"@angular/core","name":"Component","line":23,"character":1},"arguments":[{"selector":"gd-signature-component","template":"<div class=\"gd-signature\" *ngIf=\"!isDigital()\"\n     (clickOutside)=\"hideMenu($event)\"\n     [exclude]=\"'gd-context-menu,.ui-resizable-handle'\"\n     [excludeBeforeClick]=\"true\"\n     [clickOutsideEvents]=\"'mousedown'\"\n     [clickOutsideEnabled]=\"active\"\n     [style.left.px]=\"position.left\" [style.top.px]=\"position.top\"\n     [style.width.px]=\"data.width ? data.width : undefined\"\n     [style.height.px]=\"data.height ? data.height : undefined\" (click)=\"activation()\">\n  <div [draggable]=\"true\" (dragover)=\"dragOver($event)\" (dragstart)=\"dragStart($event)\"\n       (drag)=\"dragging($event)\" (dragend)=\"dragging($event)\" (drop)=\"drop($event)\"\n       (panstart)=\"dragStart($event)\" (panmove)=\"dragging($event)\"\n       class=\"gd-signature-wrapper\">\n    <gd-context-menu *ngIf=\"active\" [topPosition]=\"position.top\" [textMenu]=\"isText()\" [formatting]=\"getFormatting()\"\n                     (changeFormatting)=\"saveTextSignature($event)\" (removeSign)=\"remove()\" (copySign)=\"onCopySign()\"\n                     [lock]=\"!unlock\" (lockOut)=\"unlock = !$event\" [translation]=\"getMenuShift()\"></gd-context-menu>\n    <img class=\"gd-signature-image\" *ngIf=\"!isText()\" [attr.src]=\"getData()\" alt>\n    <textarea class=\"gd-text\" *ngIf=\"isText()\" [value]=\"data.props?.text\"\n              id=\"text\" #text (keyup)=\"saveText(text.value)\"\n              [style.text-decoration]=\"data.props?.underline ? 'underline' : 'unset'\"\n              [style.font-style]=\"data.props?.italic ? 'italic' : 'unset'\"\n              [style.font-weight]=\"data.props?.bold ? 'bold' : 'unset'\"\n              [style.color]=\"data.props?.fontColor\"\n              [style.font-family]=\"data?.props.font\"\n              [style.font-size.px]=\"data?.props.fontSize\"\n              [style.width.px]=\"data.width ? data.width : undefined\"\n              [style.height.px]=\"data.height ? data.height : undefined\"></textarea>\n  </div>\n  <gd-resizing [id]=\"id\" *ngIf=\"active\" [init]=\"isInit()\"\n               (offsetX)=\"width($event)\" (offsetY)=\"height($event)\"\n               (offsetTop)=\"top($event)\" (offsetLeft)=\"left($event)\"\n               [se]=\"true\" [sw]=\"unlock\" [ne]=\"unlock\" [nw]=\"unlock\"\n               [pageHeight]=\"pageHeight\" [pageWidth]=\"pageWidth\"></gd-resizing>\n</div>\n<div class=\"gd-digital-marker\" *ngIf=\"isDigital()\">\n  <fa-icon [icon]=\"['fas','info-circle']\" [class]=\"'ng-fa-icon icon'\"></fa-icon>\n  <div>Digitally signed : {{data.digitalProps.contact ? data.digitalProps.contact : data.digitalProps.reason}}</div>\n  <fa-icon [icon]=\"['fas','times']\" [class]=\"'ng-fa-icon icon'\" (click)=\"remove()\"></fa-icon>\n</div>\n","styles":[".gd-signature{position:absolute!important}.gd-signature .gd-signature-wrapper{height:inherit;outline:#679ffa solid 1px}.gd-signature-image{width:100%!important;height:inherit}.gd-text{width:inherit;height:inherit;border:none;resize:none;outline:0;margin:0;padding:0}.gd-digital-marker{background-color:#3787f5;height:16px;width:100%;text-align:left;display:flex;position:absolute;bottom:0}.gd-digital-marker .icon{color:#fff;font-size:10px;margin:0 5px 0 3px}.gd-digital-marker div{flex-grow:1;font-size:8px;color:#fff;margin-top:1px}"]}]}],"members":{"id":[{"__symbolic":"property","decorators":[{"__symbolic":"call","expression":{"__symbolic":"reference","module":"@angular/core","name":"Input","line":29,"character":3}}]}],"data":[{"__symbolic":"property","decorators":[{"__symbolic":"call","expression":{"__symbolic":"reference","module":"@angular/core","name":"Input","line":30,"character":3}}]}],"position":[{"__symbolic":"property","decorators":[{"__symbolic":"call","expression":{"__symbolic":"reference","module":"@angular/core","name":"Input","line":31,"character":3}}]}],"type":[{"__symbolic":"property","decorators":[{"__symbolic":"call","expression":{"__symbolic":"reference","module":"@angular/core","name":"Input","line":32,"character":3}}]}],"pageWidth":[{"__symbolic":"property","decorators":[{"__symbolic":"call","expression":{"__symbolic":"reference","module":"@angular/core","name":"Input","line":33,"character":3}}]}],"pageHeight":[{"__symbolic":"property","decorators":[{"__symbolic":"call","expression":{"__symbolic":"reference","module":"@angular/core","name":"Input","line":34,"character":3}}]}],"__ctor__":[{"__symbolic":"constructor","parameters":[{"__symbolic":"reference","name":"SignatureService"},{"__symbolic":"reference","name":"RemoveSignatureService"},{"__symbolic":"reference","name":"CopySignatureService"},{"__symbolic":"reference","name":"ActiveSignatureService"},{"__symbolic":"reference","name":"SignaturesHolderService"}]}],"ngOnInit":[{"__symbolic":"method"}],"getData":[{"__symbolic":"method"}],"dragOver":[{"__symbolic":"method"}],"dragStart":[{"__symbolic":"method"}],"dragging":[{"__symbolic":"method"}],"isOnPage":[{"__symbolic":"method"}],"isText":[{"__symbolic":"method"}],"getFormatting":[{"__symbolic":"method"}],"saveTextSignature":[{"__symbolic":"method"}],"fillFormatting":[{"__symbolic":"method"}],"remove":[{"__symbolic":"method"}],"activation":[{"__symbolic":"method"}],"isDigital":[{"__symbolic":"method"}],"width":[{"__symbolic":"method"}],"height":[{"__symbolic":"method"}],"left":[{"__symbolic":"method"}],"top":[{"__symbolic":"method"}],"notifyChanges":[{"__symbolic":"method"}],"drop":[{"__symbolic":"method"}],"isInit":[{"__symbolic":"method"}],"onCopySign":[{"__symbolic":"method"}],"ngAfterViewInit":[{"__symbolic":"method"}],"correctPosition":[{"__symbolic":"method"}],"saveText":[{"__symbolic":"method"}],"sendSaveText":[{"__symbolic":"method"}],"hideMenu":[{"__symbolic":"method"}],"getMenuShift":[{"__symbolic":"method"}]}},"ɵf":{"__symbolic":"class","decorators":[{"__symbolic":"call","expression":{"__symbolic":"reference","module":"@angular/core","name":"Component","line":6,"character":1},"arguments":[{"selector":"gd-context-menu","template":"<div class=\"gd-context-menu\" [ngStyle]=\"isMobile ? null : {transform: 'translateX(' + translation + 'px)'}\"\n     [ngClass]=\"topPosition > 10 ? 'gd-context-menu-top' : 'gd-context-menu-bottom'\">\n  <gd-button [icon]=\"'arrows-alt'\" [class]=\"'ng-fa-icon icon arrows'\" [iconSize]=\"'sm'\"></gd-button>\n  <gd-text-menu *ngIf=\"textMenu\" [blur]=\"isMobile\" [color]=\"formatting.color\" [bold]=\"formatting.bold\"\n                [font]=\"formatting.font\" [fontSize]=\"formatting.fontSize\" [italic]=\"formatting.italic\"\n                [underline]=\"formatting.underline\" (outBold)=\"toggleBold($event)\"\n                (outUnderline)=\"toggleUnderline($event)\" (outItalic)=\"toggleItalic($event)\"\n                (outColor)=\"selectColor($event)\" (outFont)=\"selectFont($event)\"\n                (outFontSize)=\"selectFontSize($event)\"></gd-text-menu>\n  <gd-button [icon]=\"lock ? 'lock' : 'unlock'\" [class]=\"'ng-fa-icon icon'\" (click)=\"toggleLock()\"></gd-button>\n  <gd-button [icon]=\"'copy'\" [class]=\"'ng-fa-icon icon'\" (click)=\"onCopySign()\"></gd-button>\n  <gd-button [icon]=\"'trash'\" [class]=\"'ng-fa-icon icon'\" [iconSize]=\"'sm'\" (click)=\"deleteSign()\"></gd-button>\n</div>\n","styles":[".gd-context-menu-top{top:-44px}.gd-context-menu-bottom{bottom:-40px}.gd-context-menu{box-shadow:rgba(0,0,0,.52) 0 0 5px;background-color:#fff;position:absolute;left:0;right:0;margin:auto;cursor:default;width:max-content;width:-moz-max-content;width:-webkit-max-content;display:flex;flex-direction:row;z-index:999}.gd-context-menu .arrows{cursor:move}.gd-context-menu ::ng-deep .active{background-color:#e7e7e7}.gd-context-menu ::ng-deep .icon-button{margin:0!important}@media (max-width:1037px){.gd-context-menu-top{top:-34px}}"]}]}],"members":{"formatting":[{"__symbolic":"property","decorators":[{"__symbolic":"call","expression":{"__symbolic":"reference","module":"@angular/core","name":"Input","line":12,"character":3}}]}],"textMenu":[{"__symbolic":"property","decorators":[{"__symbolic":"call","expression":{"__symbolic":"reference","module":"@angular/core","name":"Input","line":13,"character":3}}]}],"topPosition":[{"__symbolic":"property","decorators":[{"__symbolic":"call","expression":{"__symbolic":"reference","module":"@angular/core","name":"Input","line":14,"character":3}}]}],"lock":[{"__symbolic":"property","decorators":[{"__symbolic":"call","expression":{"__symbolic":"reference","module":"@angular/core","name":"Input","line":15,"character":3}}]}],"translation":[{"__symbolic":"property","decorators":[{"__symbolic":"call","expression":{"__symbolic":"reference","module":"@angular/core","name":"Input","line":16,"character":3}}]}],"changeFormatting":[{"__symbolic":"property","decorators":[{"__symbolic":"call","expression":{"__symbolic":"reference","module":"@angular/core","name":"Output","line":17,"character":3}}]}],"removeSign":[{"__symbolic":"property","decorators":[{"__symbolic":"call","expression":{"__symbolic":"reference","module":"@angular/core","name":"Output","line":18,"character":3}}]}],"copySign":[{"__symbolic":"property","decorators":[{"__symbolic":"call","expression":{"__symbolic":"reference","module":"@angular/core","name":"Output","line":19,"character":3}}]}],"lockOut":[{"__symbolic":"property","decorators":[{"__symbolic":"call","expression":{"__symbolic":"reference","module":"@angular/core","name":"Output","line":20,"character":3}}]}],"__ctor__":[{"__symbolic":"constructor","parameters":[{"__symbolic":"reference","module":"@groupdocs.examples.angular/common-components","name":"WindowService","line":24,"character":38}]}],"ngOnInit":[{"__symbolic":"method"}],"saveChanges":[{"__symbolic":"method"}],"selectFontSize":[{"__symbolic":"method"}],"selectFont":[{"__symbolic":"method"}],"selectColor":[{"__symbolic":"method"}],"toggleBold":[{"__symbolic":"method"}],"toggleItalic":[{"__symbolic":"method"}],"toggleUnderline":[{"__symbolic":"method"}],"deleteSign":[{"__symbolic":"method"}],"toggleLock":[{"__symbolic":"method"}],"onCopySign":[{"__symbolic":"method"}]}},"ɵg":{"__symbolic":"class","decorators":[{"__symbolic":"call","expression":{"__symbolic":"reference","module":"@angular/core","name":"Component","line":3,"character":1},"arguments":[{"selector":"gd-canvas","template":"<div class=\"bc-paint-container\">\n  <div class=\"bc-paint-canvas-container\">\n    <canvas #canvas (mousedown)=\"onMouseDown($event)\" (mousemove)=\"onMouseMove($event)\"\n            (mouseup)=\"onMouseUp($event)\" (mouseleave)=\"onMouseUp($event)\" [width]=\"getWidth()\"\n            [height]=\"getHeight()\" (panstart)=\"onMouseDown($event)\" (panmove)=\"onMouseMove($event)\"\n            (panend)=\"onMouseUp($event)\"></canvas>\n  </div>\n</div>\n","styles":[".bc-paint-canvas-container,.bc-paint-container{width:100%;height:100%}@media (max-width:1037px){.bc-paint-canvas-container>canvas{width:100%;height:100%;border:0}}"]}]}],"members":{"color":[{"__symbolic":"property","decorators":[{"__symbolic":"call","expression":{"__symbolic":"reference","module":"@angular/core","name":"Input","line":10,"character":3}}]}],"canvas":[{"__symbolic":"property","decorators":[{"__symbolic":"call","expression":{"__symbolic":"reference","module":"@angular/core","name":"ViewChild","line":16,"character":3},"arguments":["canvas",{"static":true}]}]}],"__ctor__":[{"__symbolic":"constructor","parameters":[{"__symbolic":"reference","module":"@groupdocs.examples.angular/common-components","name":"WindowService","line":18,"character":38}]}],"ngOnInit":[{"__symbolic":"method"}],"onMouseDown":[{"__symbolic":"method"}],"onMouseUp":[{"__symbolic":"method"}],"onMouseMove":[{"__symbolic":"method"}],"setColor":[{"__symbolic":"method"}],"getImage":[{"__symbolic":"method"}],"clear":[{"__symbolic":"method"}],"ngOnChanges":[{"__symbolic":"method"}],"getWidth":[{"__symbolic":"method"}],"getHeight":[{"__symbolic":"method"}]}},"ɵh":{"__symbolic":"class","decorators":[{"__symbolic":"call","expression":{"__symbolic":"reference","module":"@angular/core","name":"Component","line":6,"character":1},"arguments":[{"selector":"gd-stamp-canvas","template":"<div [clickOutsideEnabled]=\"active\" [clickOutsideEvents]=\"'mousedown'\"\n     (clickOutside)=\"inactive($event)\">\n  <div class=\"gd-stamp-box\" [style.left.px]=\"getLeft()\" [style.top.px]=\"getTop()\" [style.z-index]=\"props.zIndex\">\n    <div class=\"gd-context-menu\" *ngIf=\"active\" [ngStyle]=\"isMobile ? null : {transform: 'translateX(' + getTranslation() + 'px)'}\">\n      <gd-button name=\"button\" class=\"first-element\" [icon]=\"'fill-drip'\" [tooltip]=\"'Color'\" (click)=\"toggleColorPicker($event, true)\">\n        <div class=\"bg-color-pic\" [style.background-color]=\"props.backgroundColor\"></div>\n      </gd-button>\n      <gd-color-picker [isOpen]=\"colorPickerBG\" (closeOutside)=\"closeColorPickerBG($event)\"\n                       [className]=\"'palette'\"\n                       (selectedColor)=\"selectColor(true, $event)\"></gd-color-picker>\n      <gd-select class=\"csg-border-width\" [options]=\"borderWidth\" (selected)=\"selectBorderWidth($event)\"\n                 [showSelected]=\"{name: props.strokeWidth + 'px', value: props.strokeWidth}\"></gd-select>\n      <gd-button name=\"button\" [icon]=\"'square'\" [iconRegular]=\"true\" [tooltip]=\"'Color'\"\n                 (click)=\"toggleColorPicker($event, false)\" class=\"color-for-shape\">\n        <div class=\"bg-color-pic\" [style.background-color]=\"props.strokeColor\"></div>\n      </gd-button>\n      <gd-color-picker [isOpen]=\"colorPickerC\" (closeOutside)=\"closeColorPickerC($event)\"\n                       [className]=\"'palette'\"\n                       (selectedColor)=\"selectColor(false, $event)\"></gd-color-picker>\n      <gd-button name=\"button\" class=\"stamp-trash\" [icon]=\"'trash'\" [tooltip]=\"'Delete'\" [iconSize]=\"'sm'\" (click)=\"deleteCanvas()\">\n      </gd-button>\n    </div>\n    <div class=\"csg-bounding-box\" [ngClass]=\"active ? 'active' : ''\" [style.width.px]=\"props.width\"\n         [style.height.px]=\"props.height\">\n      <canvas #canvas (click)=\"activation()\" class=\"csg-preview\" [width]=\"props.width\" [height]=\"props.height\"></canvas>\n      <gd-resizing [init]=\"false\" [id]=\"999\" (offsetX)=\"resize($event)\" [se]=\"true\"\n                   (release)=\"redrawCanvas()\" *ngIf=\"active\"></gd-resizing>\n    </div>\n  </div>\n</div>\n","styles":[".gd-context-menu{display:flex;height:37px;top:-40px;padding:0;background-color:#fff;cursor:default;flex-direction:row;box-shadow:rgba(0,0,0,.52) 0 0 5px}.gd-context-menu .icon{font-size:14px;cursor:pointer;color:#3e4e5a!important}.gd-context-menu ::ng-deep .dropdown-menu{top:-120px!important;height:120px;overflow-y:auto}.gd-context-menu ::ng-deep .icon-button{margin:0!important}.gd-stamp-box{position:absolute}.palette{position:absolute;top:-190px}.csg-preview{width:100%;height:100%}.csg-bounding-box{position:absolute;background-color:unset!important}.csg-bounding-box.active{border:1px solid #679ffa}.csg-border-width{width:37px!important;height:37px!important;display:flex;justify-content:center;align-items:center}.bg-color-pic{border-radius:100%;border:1px solid #ccc;position:absolute;height:8px;width:8px;right:6px;bottom:6px}::ng-deep .select{min-width:unset!important}::ng-deep .selected-value{font-size:12px!important}@media (max-width:1037px){.gd-context-menu{position:fixed;bottom:0;left:0;top:unset;right:0;width:100%;height:60px;align-items:center;padding:0;margin:0;background-color:#fff;border-top:2px solid #707070}.gd-context-menu .color-for-shape{flex:1;display:flex;align-items:center;justify-content:flex-start}.gd-context-menu .stamp-trash{flex:0 0 37px;margin-right:8px}.gd-context-menu ::ng-deep .button{margin:3px!important}.gd-context-menu ::ng-deep .select{margin:3px!important}.gd-context-menu .first-element{margin-left:8px}.csg-border-width .select{width:21px}}"]}]}],"members":{"id":[{"__symbolic":"property","decorators":[{"__symbolic":"call","expression":{"__symbolic":"reference","module":"@angular/core","name":"Input","line":12,"character":3}}]}],"theFirst":[{"__symbolic":"property","decorators":[{"__symbolic":"call","expression":{"__symbolic":"reference","module":"@angular/core","name":"Input","line":13,"character":3}}]}],"active":[{"__symbolic":"property","decorators":[{"__symbolic":"call","expression":{"__symbolic":"reference","module":"@angular/core","name":"Input","line":14,"character":3}}]}],"props":[{"__symbolic":"property","decorators":[{"__symbolic":"call","expression":{"__symbolic":"reference","module":"@angular/core","name":"Input","line":15,"character":3}}]}],"width":[{"__symbolic":"property","decorators":[{"__symbolic":"call","expression":{"__symbolic":"reference","module":"@angular/core","name":"Input","line":16,"character":3}}]}],"height":[{"__symbolic":"property","decorators":[{"__symbolic":"call","expression":{"__symbolic":"reference","module":"@angular/core","name":"Input","line":17,"character":3}}]}],"canvas":[{"__symbolic":"property","decorators":[{"__symbolic":"call","expression":{"__symbolic":"reference","module":"@angular/core","name":"ViewChild","line":20,"character":3},"arguments":["canvas",{"static":true}]}]}],"__ctor__":[{"__symbolic":"constructor","parameters":[{"__symbolic":"reference","name":"ActiveCanvasService"},{"__symbolic":"reference","name":"ɵi"},{"__symbolic":"reference","module":"@groupdocs.examples.angular/common-components","name":"OnCloseService","line":28,"character":39},{"__symbolic":"reference","module":"@groupdocs.examples.angular/common-components","name":"WindowService","line":29,"character":38}]}],"activation":[{"__symbolic":"method"}],"ngOnInit":[{"__symbolic":"method"}],"ngAfterViewInit":[{"__symbolic":"method"}],"redrawCanvas":[{"__symbolic":"method"}],"fontDecoration":[{"__symbolic":"method"}],"makeTextUnderline":[{"__symbolic":"method"}],"drawCircle":[{"__symbolic":"method"}],"drawTextCircle":[{"__symbolic":"method"}],"refreshRadius":[{"__symbolic":"method"}],"toggleColorPicker":[{"__symbolic":"method"}],"selectColor":[{"__symbolic":"method"}],"selectBorderWidth":[{"__symbolic":"method"}],"deleteCanvas":[{"__symbolic":"method"}],"getLeft":[{"__symbolic":"method"}],"getTop":[{"__symbolic":"method"}],"calcDiff":[{"__symbolic":"method"}],"resize":[{"__symbolic":"method"}],"closeColorPickerBG":[{"__symbolic":"method"}],"closeColorPickerC":[{"__symbolic":"method"}],"getTranslation":[{"__symbolic":"method"}],"inactive":[{"__symbolic":"method"}]}},"ɵi":{"__symbolic":"class","members":{"__ctor__":[{"__symbolic":"constructor"}],"remove":[{"__symbolic":"method"}]}},"ɵj":{"__symbolic":"class","decorators":[{"__symbolic":"call","expression":{"__symbolic":"reference","module":"@angular/core","name":"Component","line":6,"character":1},"arguments":[{"selector":"gd-text-menu","template":"<div class=\"gd-text-menu\">\n  <gd-select class=\"format-select first-component\" [options]=\"fontOptions\"\n             (selected)=\"selectFont($event)\"\n             [showSelected]=\"{name : font, value : font}\"></gd-select>\n  <gd-select class=\"format-select\" [options]=\"fontSizeOptions\"\n             (selected)=\"selectFontSize($event)\"\n             [showSelected]=\"{name : fontSize + 'px', value : fontSize}\"></gd-select>\n  <gd-button [icon]=\"'bold'\" [tooltip]=\"'Bold'\" *ngIf=\"decoration\"\n             (click)=\"toggleBold($event)\" [toggle]=\"bold\"></gd-button>\n  <gd-button [icon]=\"'italic'\" [tooltip]=\"'Italic'\" *ngIf=\"decoration\"\n             (click)=\"toggleItalic($event)\" [toggle]=\"italic\"></gd-button>\n  <gd-button [icon]=\"'underline'\" [tooltip]=\"'Underline'\" *ngIf=\"decoration\"\n             (click)=\"toggleUnderline($event)\" [toggle]=\"underline\"></gd-button>\n  <gd-button name=\"button\" class=\"color-for-text\" [icon]=\"'font'\" [tooltip]=\"'Color'\" (click)=\"toggleColorPicker($event)\">\n    <div class=\"bg-color-pic\" [style.background-color]=\"color\"></div>\n  </gd-button>\n  <gd-color-picker [isOpen]=\"colorPickerShow\" (closeOutside)=\"closePicker($event)\"\n                   [className]=\"'palette'\"\n                   (selectedColor)=\"selectColor($event)\"></gd-color-picker>\n  <ng-content></ng-content>\n</div>\n","styles":["::ng-deep .active{background-color:#e7e7e7}.gd-text-menu{display:flex;flex-direction:row}.gd-text-menu .format-select{height:37px;display:flex;justify-content:center;align-items:center;max-width:80px;margin:0 3px}.gd-text-menu .first-component{margin-left:8px}.gd-text-menu ::ng-deep .dropdown-menu{top:40px!important;height:120px;overflow-y:auto}.gd-text-menu ::ng-deep .icon-button{margin:0!important}.bg-color-pic{border-radius:100%;border:1px solid #ccc;position:absolute;height:8px;width:8px;right:6px;bottom:6px}.palette{position:relative;top:40px;left:-55px;z-index:100}@media (max-width:1037px){.gd-text-menu{position:fixed;bottom:0;left:0;right:0;width:100%;height:60px;align-items:center;padding:0;margin:0;background-color:#fff;border-top:2px solid #707070}.gd-text-menu ::ng-deep .selected-value{white-space:normal!important;word-wrap:break-word}.gd-text-menu .icon{color:#fff;margin:0 9px}.gd-text-menu ::ng-deep .bcPicker-palette{left:-200px;top:-200px}.gd-text-menu .palette{top:unset;bottom:40px;left:unset;right:5px}.gd-text-menu ::ng-deep .dropdown-menu{bottom:40px;top:unset!important}.gd-text-menu ::ng-deep .button{margin:3px!important}}"]}]}],"members":{"blur":[{"__symbolic":"property","decorators":[{"__symbolic":"call","expression":{"__symbolic":"reference","module":"@angular/core","name":"Input","line":12,"character":3}}]}],"fontSize":[{"__symbolic":"property","decorators":[{"__symbolic":"call","expression":{"__symbolic":"reference","module":"@angular/core","name":"Input","line":13,"character":3}}]}],"font":[{"__symbolic":"property","decorators":[{"__symbolic":"call","expression":{"__symbolic":"reference","module":"@angular/core","name":"Input","line":14,"character":3}}]}],"bold":[{"__symbolic":"property","decorators":[{"__symbolic":"call","expression":{"__symbolic":"reference","module":"@angular/core","name":"Input","line":15,"character":3}}]}],"italic":[{"__symbolic":"property","decorators":[{"__symbolic":"call","expression":{"__symbolic":"reference","module":"@angular/core","name":"Input","line":16,"character":3}}]}],"underline":[{"__symbolic":"property","decorators":[{"__symbolic":"call","expression":{"__symbolic":"reference","module":"@angular/core","name":"Input","line":17,"character":3}}]}],"color":[{"__symbolic":"property","decorators":[{"__symbolic":"call","expression":{"__symbolic":"reference","module":"@angular/core","name":"Input","line":18,"character":3}}]}],"decoration":[{"__symbolic":"property","decorators":[{"__symbolic":"call","expression":{"__symbolic":"reference","module":"@angular/core","name":"Input","line":19,"character":3}}]}],"outFontSize":[{"__symbolic":"property","decorators":[{"__symbolic":"call","expression":{"__symbolic":"reference","module":"@angular/core","name":"Output","line":21,"character":3}}]}],"outFont":[{"__symbolic":"property","decorators":[{"__symbolic":"call","expression":{"__symbolic":"reference","module":"@angular/core","name":"Output","line":22,"character":3}}]}],"outBold":[{"__symbolic":"property","decorators":[{"__symbolic":"call","expression":{"__symbolic":"reference","module":"@angular/core","name":"Output","line":23,"character":3}}]}],"outItalic":[{"__symbolic":"property","decorators":[{"__symbolic":"call","expression":{"__symbolic":"reference","module":"@angular/core","name":"Output","line":24,"character":3}}]}],"outUnderline":[{"__symbolic":"property","decorators":[{"__symbolic":"call","expression":{"__symbolic":"reference","module":"@angular/core","name":"Output","line":25,"character":3}}]}],"outColor":[{"__symbolic":"property","decorators":[{"__symbolic":"call","expression":{"__symbolic":"reference","module":"@angular/core","name":"Output","line":26,"character":3}}]}],"__ctor__":[{"__symbolic":"constructor","parameters":[{"__symbolic":"reference","module":"@groupdocs.examples.angular/common-components","name":"OnCloseService","line":33,"character":39}]}],"ngOnInit":[{"__symbolic":"method"}],"selectFontSize":[{"__symbolic":"method"}],"selectFont":[{"__symbolic":"method"}],"toggleColorPicker":[{"__symbolic":"method"}],"selectColor":[{"__symbolic":"method"}],"toggleBold":[{"__symbolic":"method"}],"toggleItalic":[{"__symbolic":"method"}],"toggleUnderline":[{"__symbolic":"method"}],"closePicker":[{"__symbolic":"method"}]}},"ɵk":{"__symbolic":"class","decorators":[{"__symbolic":"call","expression":{"__symbolic":"reference","module":"@angular/core","name":"Component","line":4,"character":1},"arguments":[{"selector":"gd-signature-left-panel","template":"<gd-left-side-bar [showSpinner]=\"loading\">\n  <div class=\"tab-content\">\n    <div class=\"gd-signature-context-panel\">\n      <div class=\"gd-signature-context-pane-wrapper\">\n        <div class=\"signature-title-block\"> <!--for safari-->\n          <div class=\"gd-signature-list-title\" *ngIf=\"showNewCode || showUpload\">\n            <div class=\"gd-signature-context-panel-title\">{{getTitle()}}</div>\n            <div class=\"gd-signature-title-icon\">\n              <fa-icon [icon]=\"['fa','times']\" [class]=\"'ng-fa-icon icon'\" (click)=\"closeNewSignature()\"></fa-icon>\n            </div>\n          </div>\n        </div>\n        <gd-upload-signature (closePanel)=\"closeUploadPanel($event)\" [rewrite]=\"rewrite\" [signatureType]=\"id\"\n                             *ngIf=\"showUpload\"></gd-upload-signature>\n        <gd-new-bar-qr-code (closePanel)=\"closeCodePanel($event)\" [type]=\"id\" [icon]=\"icon()\" [name]=\"getCodeName()\"\n                            *ngIf=\"showNewCode\"></gd-new-bar-qr-code>\n        <div class=\"signature-title-block\"> <!--for safari-->\n          <div class=\"gd-signature-list-title\">\n            <div class=\"gd-signature-context-panel-title\">{{getName()}}</div>\n            <div class=\"gd-signature-title-icon\">\n              <fa-icon [icon]=\"['fa','plus']\" [class]=\"'ng-fa-icon icon'\"\n                       [ngClass]=\"showNewCode || showUpload ? 'disabled' : ''\"\n                       (click)=\"openNewSignature()\"></fa-icon>\n            </div>\n          </div>\n        </div>\n        <gd-signature-list-panel class=\"gd-signatures-scroll\" [icon]=\"icon()\" [signatureType]=\"id\"\n                                 [signatures]=\"signatures\"\n                                 (removeSignatureEvent)=\"removeSignature($event, id)\"\n                                 [isPdf]=\"isPdf\" [loading]=\"loading\"></gd-signature-list-panel>\n      </div>\n    </div>\n  </div>\n</gd-left-side-bar>\n","styles":["::ng-deep .left-panel{width:350px;height:calc(100% - 90px)}::ng-deep .gd-left-bar-fade{width:350px!important}.gd-signatures-scroll{height:calc(100% - 60px)}.tab-content{height:calc(100% - 90px);line-height:unset;position:absolute;background-color:#fff}.gd-signature-context-panel{background-color:#f3f3f3;width:350px;height:100%;position:absolute}.gd-signature-context-panel-title,.gd-signature-context-upload-title{color:#aaa;font-size:12px;font-family:Helvetica;font-weight:700;margin:5px 12px}.signature-title-block{display:block}.gd-signature-list-title{display:flex;flex-direction:row;height:70px}.gd-signature-list-title .gd-signature-title-icon{flex:0 0 70px;display:flex;align-items:center;justify-content:center}.gd-signature-list-title .gd-signature-title-icon .icon{color:#707070;cursor:pointer;font-size:12px}.gd-signature-list-title .gd-signature-title-icon .icon.disabled{color:#959da5}.gd-signature-list-title .gd-signature-context-panel-title{flex:1;display:flex;align-items:center;justify-content:flex-start}.gd-signature-context-pane-wrapper{display:flex;flex-direction:column;height:inherit;overflow:auto}@media (max-width:1037px){.tab-content{width:100%;height:calc(100% - 120px)!important}::ng-deep .left-panel{width:100%!important;overflow:auto!important;height:calc(100% - 120px)}.gd-signature-context-panel{left:0;right:0;width:auto}.gd-signature-context-panel-title{font-size:12px;line-height:18px;margin:16px 0 14px 12px}.gd-signature-context-panel-title,.gd-signature-context-upload-title{width:unset}}"]}]}],"members":{"rewrite":[{"__symbolic":"property","decorators":[{"__symbolic":"call","expression":{"__symbolic":"reference","module":"@angular/core","name":"Input","line":10,"character":3}}]}],"isPdf":[{"__symbolic":"property","decorators":[{"__symbolic":"call","expression":{"__symbolic":"reference","module":"@angular/core","name":"Input","line":11,"character":3}}]}],"id":[{"__symbolic":"property","decorators":[{"__symbolic":"call","expression":{"__symbolic":"reference","module":"@angular/core","name":"Input","line":12,"character":3}}]}],"newSignatureEvent":[{"__symbolic":"property","decorators":[{"__symbolic":"call","expression":{"__symbolic":"reference","module":"@angular/core","name":"Output","line":13,"character":3}}]}],"__ctor__":[{"__symbolic":"constructor","parameters":[{"__symbolic":"reference","name":"SignatureService"}]}],"getSignatures":[{"__symbolic":"method"}],"ngOnInit":[{"__symbolic":"method"}],"init":[{"__symbolic":"method"}],"getTitleIcon":[{"__symbolic":"method"}],"getTitle":[{"__symbolic":"method"}],"getName":[{"__symbolic":"method"}],"removeSignature":[{"__symbolic":"method"}],"closeUploadPanel":[{"__symbolic":"method"}],"closeCodePanel":[{"__symbolic":"method"}],"getCodeName":[{"__symbolic":"method"}],"icon":[{"__symbolic":"method"}],"ngOnChanges":[{"__symbolic":"method"}],"closeNewSignature":[{"__symbolic":"method"}],"openNewSignature":[{"__symbolic":"method"}]}},"ɵl":{"__symbolic":"class","decorators":[{"__symbolic":"call","expression":{"__symbolic":"reference","module":"@angular/core","name":"Component","line":7,"character":1},"arguments":[{"selector":"gd-hand-modal","template":"<gd-modal [id]=\"'gd-draw-hand-signature'\" [title]=\"'Draw signature'\" (visible)=\"onCloseOpen(canvasComponent, $event)\">\n  <div class=\"paint-body\">\n    <div class=\"bc-paint-header\">\n      <div class=\"bc-paint-palette\">\n        <gd-button name=\"button\" [icon]=\"'fill'\" [tooltip]=\"'Pencil color'\"\n                   (click)=\"toggleColorPicker($event)\">\n          <div class=\"bg-color-pic\" [style.background-color]=\"selectedColor\"></div>\n        </gd-button>\n        <gd-color-picker [isOpen]=\"colorPickerShow\" (closeOutside)=\"closePicker($event)\"\n                         [className]=\"'palette'\"\n                         (selectedColor)=\"selectColor($event)\"></gd-color-picker>\n      </div>\n      <div class=\"bc-paint-export\" (click)=\"saveSign(canvasComponent)\">\n        <fa-icon [icon]=\"['fa','save']\" [class]=\"'ng-fa-icon icon'\"></fa-icon>\n        <span class=\"save-button\">Save</span>\n      </div>\n    </div>\n    <div class=\"gd-draw-image\">\n      <gd-canvas #canvasComponent [color]=\"selectedColor\"></gd-canvas>\n    </div>\n  </div>\n</gd-modal>\n","styles":[".paint-body{width:1036px;height:561px}.paint-body ::ng-deep .button{font-size:unset!important;color:#3e4e5a!important}.paint-body ::ng-deep .button ::ng-deep .text{padding-left:0!important}.gd-draw-image{background-image:url(data:image/png;base64,iVBORw0KGgoAAAANSUhEUgAAACAAAAAhCAYAAAC4JqlRAAAACXBIWXMAAA7EAAAOxAGVKw4bAAAA4UlEQVR4nO2WbQuDMAyE+///q0WhKiiacYFK7BeXK2OMJXC2SF8er2kwiTPO81St6yo5ZxmGQdsnYZwdi/6yLJICIAACIAAC4KcA6uYMgN34BmAX9QgA9atYuQGO47j6mMw4YDXPsyQ8PCqlaAsAuNAjdYC1DyDeY7MOQuoAY10L0CboO0KoAywA6NsFn26QBaUB6hFYAO8VrhEAAfC/APQ1tJXQC9CCXABsKQZAW1qpStgDwG7+kVL8dQBPAnYDQN4cwFgrvFOAfd/Fq23b9IdiHEeZpokWAF41ugKO5u7gN6EQAAAFZL5NAAAAAElFTkSuQmCC)!important;position:absolute;padding:0!important;background-color:#fff;overflow:hidden;overflow-y:auto;width:inherit}.bc-paint-header{height:60px;width:100%;display:flex;justify-content:space-between;align-items:center}.bg-color-pic{border-radius:100%;border:1px solid #ccc;position:absolute;height:8px;width:8px;right:6px;bottom:6px}::ng-deep .bcPicker-palette{position:absolute}.bc-paint-export{background-color:#25c2d4;margin-right:10px;width:68px;height:37px;display:flex;justify-content:space-between;color:#fff;align-items:center;cursor:pointer}.bc-paint-export .icon{display:flex;text-align:center;justify-content:center;flex:0 0 27px}.bc-paint-export .save-button{font-size:10px;display:flex;text-align:center;justify-content:center;flex:0 0 40px}@media (max-width:1037px){.paint-body{width:inherit;height:inherit}}"]}]}],"members":{"__ctor__":[{"__symbolic":"constructor","parameters":[{"__symbolic":"reference","name":"SignatureService"},{"__symbolic":"reference","name":"SignatureTabActivatorService"},{"__symbolic":"reference","module":"@groupdocs.examples.angular/common-components","name":"ModalService","line":19,"character":37}]}],"ngOnInit":[{"__symbolic":"method"}],"selectColor":[{"__symbolic":"method"}],"saveSign":[{"__symbolic":"method"}],"close":[{"__symbolic":"method"}],"toggleColorPicker":[{"__symbolic":"method"}],"closePicker":[{"__symbolic":"method"}],"onCloseOpen":[{"__symbolic":"method"}],"clear":[{"__symbolic":"method"}]}},"ɵm":{"__symbolic":"class","decorators":[{"__symbolic":"call","expression":{"__symbolic":"reference","module":"@angular/core","name":"Component","line":16,"character":1},"arguments":[{"selector":"gd-stamp-modal","template":"<gd-modal [id]=\"'gd-draw-stamp-signature'\" [title]=\"'Compose stamp'\" (visible)=\"onCloseOpen($event)\">\n  <div class=\"stamp-body\">\n    <div class=\"stamp-header\">\n      <div class=\"header-buttons\">\n        <gd-button [icon]=\"'circle'\" (click)=\"addCanvas()\" [iconRegular]=\"true\">\n          <fa-icon class=\"plus\" [icon]=\"['fas','plus']\"></fa-icon>\n        </gd-button>\n        <gd-button [icon]=\"'font'\" (click)=\"toggleText()\">\n          <fa-icon class=\"plus\" [icon]=\"['fas','plus']\"></fa-icon>\n        </gd-button>\n      </div>\n      <div class=\"stamp-export\" (click)=\"saveSign()\">\n        <fa-icon [icon]=\"['fa','save']\" [class]=\"'ng-fa-icon icon'\"></fa-icon>\n        <span class=\"save-button\">Save</span>\n      </div>\n    </div>\n    <div class=\"gd-draw-stamp\" [style.width.px]=\"getWidth()\" [style.height.px]=\"getHeight()\">\n      <div gdHostDynamic [ident]=\"999999\"></div>\n      <div class=\"gd-draw-stamp-text\" *ngIf=\"showText\" [clickOutsideEnabled]=\"showText\"\n           [clickOutsideEvents]=\"'mousedown'\" (clickOutside)=\"text.value ? addText(text.value) : leaveText($event)\">\n        <div class=\"gd-text-menu-context\">\n          <gd-text-menu [blur]=\"true\" [color]=\"textProps.color\" [bold]=\"textProps.bold\"\n                        [font]=\"textProps.font\" [fontSize]=\"textProps.fontSize\" [italic]=\"textProps.italic\"\n                        [underline]=\"textProps.underline\" (outBold)=\"toggleBold($event)\"\n                        (outUnderline)=\"toggleUnderline($event)\" (outItalic)=\"toggleItalic($event)\"\n                        (outColor)=\"selectTextColor($event)\" (outFont)=\"selectFont($event)\"\n                        (outFontSize)=\"selectFontSize($event)\" [decoration]=\"false\">\n            <gd-button [icon]=\"'trash'\" [class]=\"'ng-fa-icon icon'\" [iconSize]=\"'sm'\"\n                       (click)=\"deleteText()\"></gd-button>\n          </gd-text-menu>\n        </div>\n        <input placeholder=\"Type your text\" id=\"text-input\"\n               #text (keyup.enter)=\"addText(text.value)\"\n               [style.text-decoration]=\"textProps?.underline ? 'underline' : 'unset'\"\n               [style.font-style]=\"textProps?.italic ? 'italic' : 'unset'\"\n               [style.font-weight]=\"textProps?.bold ? 'bold' : 'unset'\"\n               [style.color]=\"textProps?.color\"\n               [style.font-family]=\"textProps.font\"\n               [style.font-size.px]=\"textProps.fontSize\"\n               [value]=\"textString\" type=\"text\"\n               [style.width.px]=\"getTextWidth()\">\n      </div>\n    </div>\n  </div>\n</gd-modal>\n","styles":[".stamp-body{width:1036px;height:561px}.stamp-body ::ng-deep .button{font-size:unset!important;color:#3e4e5a!important}.stamp-body ::ng-deep .button ::ng-deep .text{padding-left:0!important}.stamp-body .csg-text-input{padding:5px;background-color:#e6e6e6;position:absolute;top:120px;left:0;width:calc(100% - 10px);flex-direction:row;display:flex;z-index:99999}.stamp-body .csg-text-input::after{content:\" \";width:0;height:0;border-style:solid;border-width:0 4px 5px;border-color:transparent transparent #e6e6e6;position:absolute;top:-5px;right:110px}.stamp-body .csg-text-input input{height:20px;width:100%;padding:0;margin:0 10px 0 0}.stamp-body .csg-insert-text{width:27px;height:27px;background-color:#3787f5;margin:0}.stamp-body .csg-insert-text .icon{padding:5px;color:#fff}.stamp-header{height:60px;width:100%;display:flex;justify-content:space-between;align-items:center}.header-buttons{display:flex}.header-buttons .plus{font-size:8px;position:absolute;height:5px;width:5px;right:10px;bottom:10px}.stamp-export{background-color:#25c2d4;margin-right:10px;width:68px;height:37px;display:flex;justify-content:space-between;color:#fff;align-items:center;cursor:pointer}.stamp-export .icon{display:flex;text-align:center;justify-content:center;flex:0 0 27px}.stamp-export .save-button{font-size:10px;display:flex;text-align:center;justify-content:center;flex:0 0 40px}.gd-draw-stamp{background-image:url(data:image/png;base64,iVBORw0KGgoAAAANSUhEUgAAACAAAAAhCAYAAAC4JqlRAAAACXBIWXMAAA7EAAAOxAGVKw4bAAAA4UlEQVR4nO2WbQuDMAyE+///q0WhKiiacYFK7BeXK2OMJXC2SF8er2kwiTPO81St6yo5ZxmGQdsnYZwdi/6yLJICIAACIAAC4KcA6uYMgN34BmAX9QgA9atYuQGO47j6mMw4YDXPsyQ8PCqlaAsAuNAjdYC1DyDeY7MOQuoAY10L0CboO0KoAywA6NsFn26QBaUB6hFYAO8VrhEAAfC/APQ1tJXQC9CCXABsKQZAW1qpStgDwG7+kVL8dQBPAnYDQN4cwFgrvFOAfd/Fq23b9IdiHEeZpokWAF41ugKO5u7gN6EQAAAFZL5NAAAAAElFTkSuQmCC)!important;position:absolute;padding:0!important;background-color:#fff;display:flex;justify-content:center;align-items:center}.gd-draw-stamp input{height:30px;outline:#679ffa solid 2px}.gd-draw-stamp .gd-draw-stamp-text{z-index:99999}.gd-draw-stamp .gd-text-menu-context{height:37px;top:180px;padding:0;background-color:#fff;cursor:default;position:absolute;box-shadow:rgba(0,0,0,.52) 0 0 5px}.gd-draw-stamp .gd-text-menu-context ::ng-deep .color-for-text{flex:1;display:flex;align-items:center;justify-content:flex-start}.gd-draw-stamp .gd-text-menu-context .stamp-trash{flex:0 0 37px;margin-right:8px}.gd-draw-stamp .gd-text-menu-context ::ng-deep .first-component ::ng-deep .dropdown-menu{left:8px}::ng-deep .select{color:#3e4e5a!important}::ng-deep gd-drop-down{z-index:999999!important}@media (max-width:1037px){.stamp-body{width:inherit;height:inherit}}"]}]}],"members":{"dynamicDirective":[{"__symbolic":"property","decorators":[{"__symbolic":"call","expression":{"__symbolic":"reference","module":"@angular/core","name":"ViewChild","line":26,"character":3},"arguments":[{"__symbolic":"reference","module":"@groupdocs.examples.angular/common-components","name":"HostDynamicDirective","line":26,"character":13},{"static":true}]}]}],"__ctor__":[{"__symbolic":"constructor","parameters":[{"__symbolic":"reference","module":"@groupdocs.examples.angular/common-components","name":"AddDynamicComponentService","line":33,"character":51},{"__symbolic":"reference","name":"ActiveCanvasService"},{"__symbolic":"reference","module":"@groupdocs.examples.angular/common-components","name":"WindowService","line":35,"character":38},{"__symbolic":"reference","name":"ɵi"},{"__symbolic":"reference","name":"SignatureService"},{"__symbolic":"reference","name":"SignatureTabActivatorService"},{"__symbolic":"reference","module":"@groupdocs.examples.angular/common-components","name":"ModalService","line":39,"character":37}]}],"ngOnInit":[{"__symbolic":"method"}],"saveSign":[{"__symbolic":"method"}],"close":[{"__symbolic":"method"}],"onCloseOpen":[{"__symbolic":"method"}],"clear":[{"__symbolic":"method"}],"addCircle":[{"__symbolic":"method"}],"addCanvas":[{"__symbolic":"method"}],"ngOnDestroy":[{"__symbolic":"method"}],"addText":[{"__symbolic":"method"}],"toggleText":[{"__symbolic":"method"}],"toggleUnderline":[{"__symbolic":"method"}],"toggleBold":[{"__symbolic":"method"}],"toggleItalic":[{"__symbolic":"method"}],"selectTextColor":[{"__symbolic":"method"}],"selectFont":[{"__symbolic":"method"}],"selectFontSize":[{"__symbolic":"method"}],"getWidth":[{"__symbolic":"method"}],"getHeight":[{"__symbolic":"method"}],"deleteText":[{"__symbolic":"method"}],"leaveText":[{"__symbolic":"method"}],"getTextWidth":[{"__symbolic":"method"}]}}},"origins":{"initializeApp":"./lib/signature.module","setupLoadingInterceptor":"./lib/signature.module","SignatureModule":"./lib/signature.module","SignatureAppComponent":"./lib/signature-app.component","SignatureService":"./lib/signature.service","SignatureConfigService":"./lib/signature-config.service","SignatureListPanelComponent":"./lib/signature-list-panel/signature-list-panel.component","SelectSignatureService":"./lib/select-signature.service","RemoveSignatureService":"./lib/remove-signature.service","CopySignatureService":"./lib/copy-signature.service","ActiveSignatureService":"./lib/active-signature.service","ActiveCanvasService":"./lib/active-canvas.service","SignaturesHolderService":"./lib/signatures-holder.service","SignatureTabActivatorService":"./lib/signature-tab-activator.service","DragSignatureService":"./lib/drag-signature.service","ɵa":"./lib/signature-tab/signature-tab.component","ɵb":"./lib/new-bar-qr-code/new-bar-qr-code.component","ɵc":"./lib/upload-signature/upload-signature.component","ɵd":"./lib/dnd-signature.directive","ɵe":"./lib/signature/signature.component","ɵf":"./lib/context-menu/context-menu.component","ɵg":"./lib/canvas/canvas.component","ɵh":"./lib/stamp-canvas/stamp-canvas.component","ɵi":"./lib/remove-canvas.service","ɵj":"./lib/text-menu/text-menu.component","ɵk":"./lib/signature-left-panel/signature-left-panel.component","ɵl":"./lib/hand-modal/hand-modal.component","ɵm":"./lib/stamp-modal/stamp-modal.component"},"importAs":"@groupdocs.examples.angular/signature"}